HaramDetector/IsHaram.py
HaramDetector/__init__.py
haramdetector-1.0.0.dist-info/licenses/LICENSE.lic
haramdetector-1.0.0.dist-info/METADATA
haramdetector-1.0.0.dist-info/WHEEL
haramdetector-1.0.0.dist-info/top_level.txt
haramdetector-1.0.0.dist-info/RECORD
