Metadata-Version: 2.4
Name: HaramDetector
Version: 1.0.0
Summary: Haram Detector idk
Author: holodosik
Classifier: License :: OSI Approved :: MIT License
Classifier: Programming Language :: Python :: 3
Classifier: Operating System :: OS Independent
License-File: LICENSE.lic
Dynamic: license-file
